{"0": {"pTree": {"c": [{"c": [{"c": [], "d": {"t": 4, "v": "Calendario: Vista {0} no"}, "n": "error_noview"}], "d": {}, "n": "language"}], "d": {}, "n": "window"}, "version": "0.0.9 ~ 0.1.0-beta", "Sm": [], "version_list": ["0.0.9", "0.0.9-beta", "0.1.0-beta"]}, "1": {"pTree": {"c": [{"c": [{"c": [{"c": [], "d": {"t": 4, "v": "Calendario: Direcci&oacu"}, "n": "error_where"}], "d": {}, "n": "es-ES"}], "d": {}, "n": "calendar_languages"}], "d": {}, "n": "window"}, "version": "0.1.1-RC", "Sm": [], "version_list": ["0.1.1-RC"]}, "2": {"pTree": {"c": [{"c": [{"c": [{"c": [], "d": {"t": 4, "v": "Semana"}, "n": "week"}, {"c": [], "d": {"t": 4, "v": "Calendario: Direcci\u00f3n de"}, "n": "error_where"}], "d": {}, "n": "es-ES"}], "d": {}, "n": "calendar_languages"}], "d": {}, "n": "window"}, "version": "0.2.0-RC", "Sm": [], "version_list": ["0.2.0-RC"]}, "3": {"pTree": {"c": [{"c": [{"c": [{"c": [], "d": {"t": 4, "v": "Desarrollos"}, "n": "events"}], "d": {}, "n": "es-ES"}], "d": {}, "n": "calendar_languages"}], "d": {}, "n": "window"}, "version": "0.2.2 ~ 0.2.4", "Sm": [], "version_list": ["0.2.2", "0.2.3", "0.2.4"]}, "4": {"pTree": {"c": [{"c": [{"c": [{"c": [], "d": {"t": 4, "v": "Eventos"}, "n": "events"}], "d": {}, "n": "es-ES"}], "d": {}, "n": "calendar_languages"}], "d": {}, "n": "window"}, "version": "0.2.5", "Sm": [], "version_list": ["0.2.5"]}}